tb_api/__init__.py
tb_api/cli.py
tb_api/client.py
tb_api/crossdomain.py
tb_api/exception.py
tb_api/main.py
tb_api/router.py
tb_api/script.py
tb_api/app_handler/__init__.py
tb_api/app_handler/cors.py
tb_api/loader/__init__.py
tb_api/loader/core.py
tb_api/loader/ioc.py
tb_api/loader/simple.py
tb_api/model/__init__.py
tb_api/model/config.py
tb_api/model/path.py
tb_api/model/router.py
tb_api/utils/__init__.py
tb_api/utils/config_utils.py
tb_api/utils/json_utils.py
tb_api/utils/loader_utils.py
tb_api/utils/method_utils.py
tb_api/utils/param_utils.py
tb_api/utils/response_utils.py
tb_api/utils/router_utils.py
tb_api/utils/swagger_utils.py
tb_api-1.0.9.dist-info/DESCRIPTION.rst
tb_api-1.0.9.dist-info/METADATA
tb_api-1.0.9.dist-info/RECORD
tb_api-1.0.9.dist-info/WHEEL
tb_api-1.0.9.dist-info/entry_points.txt
tb_api-1.0.9.dist-info/metadata.json
tb_api-1.0.9.dist-info/top_level.txt
