Metadata-Version: 2.0
Name: tb-api
Version: 1.0.9
Summary: Simple Flask API
Home-page: https://github.com/thongdong7/tb-api
Author: Thong Dong
Author-email: thongdong7@gmail.com
License: UNKNOWN
Platform: UNKNOWN
Classifier: Development Status :: 5 - Production/Stable
Classifier: Environment :: Console
Classifier: License :: OSI Approved :: Python Software Foundation License
Classifier: Programming Language :: Python
Classifier: Programming Language :: Python :: 3.3
Classifier: Programming Language :: Python :: 3.4
Classifier: Programming Language :: Python :: 3.5
Requires-Dist: six (==1.10.0)
Provides-Extra: client
Requires-Dist: bravado (~=8.4.0); extra == 'client'
Provides-Extra: server
Requires-Dist: click (==6.6); extra == 'server'
Requires-Dist: flask (~=0.11.1); extra == 'server'
Requires-Dist: tb-ioc (~=0.3.0); extra == 'server'
Requires-Dist: flask-cors (~=3.0.2); extra == 'server'
